{
    "results": [
		{
            "id": 31,
			"traceID": "add68eb132bddb7a5e37960716a3c47b",
			"spanID": "82d4c1e88456bde0",
			"workflowInstanceId": "UNKNOWN_WORKFLOW_ID",			
            "files": [
                "471_VALIDAZIONE_CDA2_RAD_CT25_OK.pdf"
            ]	
        },
		{
            "id": 32,
			"traceID": "1614398472b6c4962032781c7452c3ea",
			"spanID": "b4acc3c1dd0110fd",
			"workflowInstanceId": "UNKNOWN_WORKFLOW_ID",			
            "files": [
                "448_VALIDAZIONE_CDA2_RSA_CT24_OK.pdf"
            ]	
        },
		{
            "id": 39,
			"traceID": "a1d1885719ca3c1b11e01b706b81e389",
			"spanID": "6788da6c8600e0b8",
			"workflowInstanceId": "UNKNOWN_WORKFLOW_ID",			
            "files": [
                "471_VALIDAZIONE_CDA2_RAD_CT25_OK.pdf"
            ]	
        },		
		{
            "id": 40,
			"traceID": "a7ed534c2b571d3626cd881497eb1fe2",
			"spanID": "84bd70cd29739185",
			"workflowInstanceId": "UNKNOWN_WORKFLOW_ID",			
            "files": [
                "448_VALIDAZIONE_CDA2_RSA_CT24_OK.pdf"
            ]	
        },			
		{
            "id": 92,
			"traceID": "42cb33538b07cbc4f96a51dbd65994c6",
			"spanID": "2a4b807248774591",
			"workflowInstanceId": "2.16.840.1.113883.2.9.99.9.7bfd9f441a2d17ca9f637f53c964621ae392efff78eff0af3c079a8d8f766c9d.862ba4919e",			
            "files": [
                "92_VALIDAZIONE_CDA2_RAD_CT22_KO.pdf"
            ]	
        },			
		{
            "id": 448,
			"traceID": "8b28a77786a391f7b0aa77ea2daaf7bc",
			"spanID": "ee3235c0ca3347e8",
			"workflowInstanceId": "2.16.840.1.113883.2.9.99.9.2bdd653066d5b0a7e627f311b7c1ffa6d22c8ddbbd5466526e605f70db07e347.e6aa62d992^^^^urn:ihe:iti:xdw:2013:workflowInstanceId",			
            "files": [
                "448_VALIDAZIONE_CDA2_RSA_CT24_OK.pdf"
            ]
        },
		{
            "id": 461,
			"traceID": "051804937bd11a9f580798f430cd26f2",
			"spanID": "6b86c2e998ddb9a9",
			"workflowInstanceId": "2.16.840.1.113883.2.9.99.9.ee2a07d80a6fcac38a12465dddcd02ea18378dc059fbf28ba668345a5034b91f.454ab6b6e0",
            "files": [
                "461_VALIDAZIONE_CDA2_RSA_CT26_KO.pdf"
            ]	
        },					
		{
            "id": 471,
			"traceID": "34b56d40afa69f97cb6336047e245698",
			"spanID": "71a231acf5bcf0da",
			"workflowInstanceId": "2.16.840.1.113883.2.9.99.9.2b60573de8ae21c79537d64043bf2a967eb53dfa369df02ddfab93939873519d.444adf945e^^^^urn:ihe:iti:xdw:2013:workflowInstanceId",			
            "files": [
                "471_VALIDAZIONE_CDA2_RAD_CT25_OK.pdf"
            ]
        }				
   ],
    "appVendor": "Factorysoft",
    "appID": "GalassiaNG",
    "appVersion": "1.0"
}
