{
  "appVendor": "ABLIA",
  "appID":"STAN",
  "appVersion": "1.0",
  "results": [
    {
      "id": 147,
      "ts": "2024-10.14T10:03:10Z",
      "traceID": "ba23745d0a2b7046",
      "workflowInstanceId": "2.16.840.1.113883.2.9.2.120.4.4.02248abcd69c9821eccd8250b48a852a24b199041b6a0ffa4e89425f6dad315b.c492c34a2a^^^^urn:ihe:iti:xdw:2013:workflowInstanceId",
      "files":[
        "42419_referto.pdf"
      ]
    },
    {
      "id": 446,
      "ts": "2024-10.14T03:23:07Z",
      "traceID": "dbbd90963020cf81",
      "workflowInstanceId": "2.16.840.1.113883.2.9.2.120.4.4.427fd8f5875704945fd96fd3babb4cfc04e90227497dd39b254c63c9f5870923.4638559f87^^^^urn:ihe:iti:xdw:2013:workflowInstanceId",
      "files":[
        "42501_referto.pdf"
      ]
    }
  ]
}