<!-- <?xml version="1.0" encoding="UTF-8"?> -->
<ClinicalDocument xmlns="urn:hl7-org:v3" xmlns:mif="urn:hl7-org:v3/mif" xmlns:xsi="http://www.w3.org/2001/XMLSchema-instance" xmlns:lab="urn:oid:1.3.6.1.4.1.19376.1.3.2" xmlns:sdtc="urn:hl7-org:sdtc">
	<realmCode code="IT"/>
	<typeId root="2.16.840.1.113883.1.3" extension="POCD_MT000040UV02"/>
	<templateId root="2.16.840.1.113883.2.9.10.1.1" extension="1.3" assigningAuthorityName="HL7 Italia"/>
	<id root="2.16.840.1.113883.2.9.2.190.4.4" extension="0019.BTANNN30S60L317Y.20260312081011.D21139" assigningAuthorityName="Regione Sicilia"/>	
	<code 	code="11502-2"	codeSystem="2.16.840.1.113883.6.1"  codeSystemName="LOINC" displayName="Referto di laboratorio"/> 
	<title> REFERTO DI LABORATORIO</title>
	<sdtc:statusCode code="active"/>
	<effectiveTime value="20260312100809+0100"/>
	<confidentialityCode code="N" codeSystem="2.16.840.1.113883.5.25" codeSystemName="HL7 Confidentiality" displayName="Normal"/>
	<languageCode code="it-IT"/>
	<setId root="2.16.840.1.113883.2.9.2.190.4.4" extension="0019.BTANNN30S60L317Y.20260312081011.D21139" assigningAuthorityName="Regione Sicilia"/> 
	<versionNumber value="1"/> 
	<recordTarget typeCode="RCT" contextControlCode="OP">
		<patientRole classCode="PAT">
			<id root="2.16.840.1.113883.2.9.4.3.2" extension="BTANNN30S60L317Y" assigningAuthorityName="MEF"/> 
			<addr use="H"> 
				<country>100</country>
				<city>PALERMO</city> 
				<streetAddressLine>VIA AMARILLI 19               </streetAddressLine> 
			</addr> 
			
			<patient> 
				<name> 
					<family>ABATE</family> 
					<given>ANTONINA</given> 
				</name> 
				<administrativeGenderCode code="F" codeSystem="2.16.840.1.113883.5.1" codeSystemName="HL7 AdministrativeGender" displayName="FEMMINA"/> 
				<birthTime value="19301120"/>
			</patient>
		</patientRole>
	</recordTarget>
	<author> 
		<time value="20260312100809+0100"/>
		<assignedAuthor classCode="ASSIGNED"> 
			<id root="2.16.840.1.113883.2.9.4.3.2" extension="PROVAX00X00X000Y" assigningAuthorityName="MEF"/> 
			<telecom use="HP" value="mail@piffero.it"/> 
			<telecom use="MC" value="0914455667788"/>
			<assignedPerson> 
				<name> 
					<family>CIPPA LIPPA</family> 
					<given>LUISELLA</given> 
					<prefix>Dr</prefix>
				</name> 
			</assignedPerson>
		</assignedAuthor> 
		</author> 
	<custodian> 
		<assignedCustodian> 
			<representedCustodianOrganization>
				<id root="2.16.840.1.113883.2.9.4.1.2" extension="433000" assigningAuthorityName="Ministero della Salute"/>	
				<name>LABORATORIO ANALISI CLINICHE DEL PIFFERO</name>
				<telecom use="WP" value="0914455667788"/> 
				<addr> 
					<country>100</country>
					<city>PALERMO</city> 
					<streetAddressLine>VIA DEL PIFFERO 26</streetAddressLine> 
				</addr>				
			</representedCustodianOrganization> 
		</assignedCustodian> 
	</custodian> 
	<legalAuthenticator> 
		<time value="20260312100809+0100"/> 
			<signatureCode code="S"/> 
			<assignedEntity>
				<id root="2.16.840.1.113883.2.9.4.3.2" extension="PROVAX00X00X000Y" assigningAuthorityName="MEF"/> 
				<addr> 
					<country>100</country>
					<city>PALERMO</city> 
					<streetAddressLine>VIA DEL PIFFERO 26</streetAddressLine>
				</addr> 
				<telecom use="HP" value="mail@piffero.it"/> 
				<telecom use="WP" value="0914455667788"/> 
				<assignedPerson> 
					<name>  
						<family>CIPPA LIPPA</family> 
						<given>LUISELLA</given>
						<prefix>Dttr.</prefix>
					</name> 
				</assignedPerson> 
			</assignedEntity> 
	</legalAuthenticator>
	<inFulfillmentOf> 
		<order classCode="ACT" moodCode="RQO"> 
			<id root="2.16.840.1.113883.2.9.4.3.4" extension="[X12032026001901]" assigningAuthorityName="Ministero delle Finanze"/> 
			<priorityCode code="R" codeSystem="2.16.840.1.113883.5.7" codeSystemName="HL7 ActPriority" displayName="routine"/>
		</order> 
	</inFulfillmentOf> 
	<component>
		<structuredBody>
			<component>
				<section ID="EMATOCHIMICA">
					<code code="19726-0" codeSystem="2.16.840.1.113883.6.1" codeSystemName="LOINC" displayName="EMATOCHIMICA"/>
					<title>EMATOCHIMICA</title>
					<component>
						<section ID="AZ">
							<code code="22664-7" codeSystem="2.16.840.1.113883.6.1" codeSystemName="LOINC" displayName="Azotemia">
							</code>
							<title>Azotemia</title>
							<text>
								<list>
									<item>
										<table ID="nota1">
											<thead>
												<tr>
													<th>Esame</th>
													<th>Risultato dell'esame</th>
													<th>Unita' di Misura</th>
													<th>Range di Riferimento</th>
												</tr>
											</thead>
											<tbody>
												<tr>
													<td>Azotemia</td>
													<td>10.00</td>
													<td>mg/dl</td>
													<td>15.00 - 50.00</td>
												</tr>
											</tbody>
										</table>
									</item>
								</list>
							</text>
							<entry typeCode="DRIV">
								<act moodCode="EVN" classCode="ACT">
									<code code="22664-7" codeSystem="2.16.840.1.113883.6.1" codeSystemName="LOINC" displayName="Azotemia"/>	
									<statusCode code="completed"/> 
									<specimen>			
										<specimenRole>
											<specimenPlayingEntity>
												<code code="BLD" codeSystem="2.16.840.1.113883.5.129" codeSystemName="SpecimenType " displayName="SANGUE"/>
											</specimenPlayingEntity>
										</specimenRole>
									</specimen>
									<entryRelationship typeCode="COMP">
										<observation moodCode="EVN" classCode="OBS">
											<code code="22664-7" codeSystem="2.16.840.1.113883.6.1" codeSystemName="LOINC" displayName="Azotemia">
											</code>										
											<statusCode code="completed"/>
											<effectiveTime value="20260312100809+0100"/>
											<value xsi:type="PQ" value="10.00" unit="mg/dl"/>
											<referenceRange>
												<observationRange>
													<value xsi:type="IVL_PQ">
														<low value="15.00" unit="mg/dl"/>
														<high value="50.00" unit="mg/dl"/>
													</value>
													<interpretationCode code="N" codeSystem="2.16.840.1.113883.5.83" codeSystemName="HL7 Observation Interpretation" displayName="Normal"/>
												</observationRange>
											</referenceRange>
										</observation>
									</entryRelationship>
									<entryRelationship typeCode="SUBJ">
										<act moodCode="EVN" classCode="ACT">
											<code code="48767-8" codeSystem="2.16.840.1.113883.6.1" codeSystemName="LOINC" displayName="Annotazioni e commenti"/>
											<text>
											<reference value="#1"/>I referti sono stati controllati e validati dal direttore sanitario

											</text>
										</act>
										</entryRelationship>
								</act>	
							</entry>
						</section>					
					</component>
				</section>
			</component>
		</structuredBody>	
	</component>
</ClinicalDocument>	
