{
  "appVendor": "exprivia",
  "appID": "eEmergency",
  "appVersion": "1",
  "results": [{
      "id": 43,
      "ts": "2023-05-25T10:43:36Z",
      "traceId": "a9d04682d8d318ef",
      "workflowInstanceId": "UNKNOWN_WORKFLOW_ID",
      "files": [
        "VALIDAZIONE_TOKEN_JWT_CAMPO_VPS_KO.pdf"
      ]
    }, {
      "id": 142,
      "ts": "2023-05-25T10:41:12Z",
      "traceId": "058e87a36c2339a6",
      "workflowInstanceId": "2.16.840.1.113883.2.9.2.30.4.4.70e309f4bcb129f1b79d438728d5b7addc66396038d7a1e83914589b92fca358.1683b76626^^^^urn:ihe:iti:xdw:2013:workflowInstanceId",
      "files": [
        "VALIDAZIONE_CDA2_VPS_CT25_KO.pdf"
      ]
    }, {
      "id": 143,
      "ts": "2023-05-25T10:36:11Z",
      "traceId": "aec7b4200d017c85",
      "workflowInstanceId": "2.16.840.1.113883.2.9.2.30.4.4.6bc765e818dbf70a6ce0b0dbeb084423471669a91d401700d68dbe6990a8ef4a.d521c7cafb^^^^urn:ihe:iti:xdw:2013:workflowInstanceId",
      "files": [
        "VALIDAZIONE_CDA2_VPS_CT26_KO.pdf"
      ]
    }
  ]
}
